{
  "country": "US",
  "currency": "USD",
  "estimateCurrency": "USD",
  "exchange": "NASDAQ NMS - GLOBAL MARKET",
  "finnhubIndustry": "Retail",
  "ipo": "1985-08-08",
  "logo": "https://static2.finnhub.io/file/publicdatany/finnhubimage/stock_logo/ROST.png",
  "marketCapitalization": 52010.188,
  "name": "Ross Stores Inc",
  "phone": "19259654400",
  "shareOutstanding": 325.23,
  "ticker": "ROST",
  "weburl": "https://www.rossstores.com/",
  "10DayAverageTradingVolume": 1.89762,
  "13WeekPriceReturnDaily": 14.4157,
  "26WeekPriceReturnDaily": 16.771,
  "3MonthADReturnStd": 20.998041,
  "3MonthAverageTradingVolume": 2.58307,
  "52WeekHigh": 162.74,
  "52WeekHighDate": "2025-11-04",
  "52WeekLow": 122.36,
  "52WeekLowDate": "2025-03-21",
  "52WeekPriceReturnDaily": 15.8289,
  "5DayPriceReturnDaily": 2.4567,
  "assetTurnoverAnnual": 1.4176,
  "assetTurnoverTTM": 1.4672,
  "beta": 1.0300299,
  "bookValuePerShareAnnual": 16.7548,
  "bookValuePerShareQuarterly": 17.6099,
  "bookValueShareGrowth5Y": 12.23,
  "capexCagr5Y": 5.33,
  "cashFlowPerShareAnnual": 4.9782,
  "cashFlowPerShareQuarterly": 5.1563,
  "cashFlowPerShareTTM": 6.24076,
  "cashPerSharePerShareAnnual": 14.3873,
  "cashPerSharePerShareQuarterly": 11.8177,
  "currentDividendYieldTTM": 0.9779,
  "currentEv/freeCashFlowAnnual": 30.3501,
  "currentEv/freeCashFlowTTM": 29.5967,
  "currentRatioAnnual": 1.6171,
  "currentRatioQuarterly": 1.5769,
  "dividendGrowthRate5Y": 7.61,
  "dividendIndicatedAnnual": 1.62,
  "dividendPerShareAnnual": 1.4721,
  "dividendPerShareTTM": 1.5468,
  "dividendYieldIndicatedAnnual": 0.9985823,
  "ebitdPerShareAnnual": 9.1617,
  "ebitdPerShareTTM": 9.3135,
  "ebitdaCagr5Y": 3.96,
  "ebitdaInterimCagr5Y": 34.44,
  "enterpriseValue": 49679.512,
  "epsAnnual": 6.3167,
  "epsBasicExclExtraItemsAnnual": 6.3167,
  "epsBasicExclExtraItemsTTM": 6.296000000000001,
  "epsExclExtraItemsAnnual": 6.3167,
  "epsExclExtraItemsTTM": 6.296000000000001,
  "epsGrowth3Y": 9.08,
  "epsGrowth5Y": 6.54,
  "epsGrowthQuarterlyYoy": -1.64,
  "epsGrowthTTMYoy": 1.54,
  "epsInclExtraItemsAnnual": 6.3167,
  "epsInclExtraItemsTTM": 6.296000000000001,
  "epsNormalizedAnnual": 6.3167,
  "epsTTM": 6.296000000000001,
  "evEbitdaTTM": 16.2813,
  "evRevenueTTM": 2.3109,
  "focfCagr5Y": 0.26,
  "forwardPE": 25.679592472896832,
  "grossMargin5Y": 25.91,
  "grossMarginAnnual": 27.78,
  "grossMarginTTM": 27.61,
  "inventoryTurnoverAnnual": 6.5824,
  "inventoryTurnoverTTM": 6.1037,
  "longTermDebt/equityAnnual": 0.275,
  "longTermDebt/equityQuarterly": 0.1774,
  "monthToDatePriceReturnDaily": 2.0828,
  "netIncomeEmployeeAnnual": 0.0195,
  "netIncomeEmployeeTTM": 0.0193,
  "netInterestCoverageAnnual": 30.7766,
  "netInterestCoverageTTM": 663.3333,
  "netMarginGrowth5Y": -0.92,
  "netProfitMargin5Y": 7.39,
  "netProfitMarginAnnual": 9.89,
  "netProfitMarginTTM": 9.6,
  "operatingMargin5Y": 9.61,
  "operatingMarginAnnual": 12.24,
  "operatingMarginTTM": 12,
  "payoutRatioAnnual": 23.38,
  "payoutRatioTTM": 24.66,
  "pb": 9.0728,
  "pbAnnual": 8.8076,
  "pbQuarterly": 8.1001,
  "pcfShareAnnual": 22.0664,
  "pcfShareTTM": 21.0225,
  "peAnnual": 24.8766,
  "peBasicExclExtraTTM": 25.213,
  "peExclExtraAnnual": 29.92984,
  "peExclExtraTTM": 25.213,
  "peInclExtraTTM": 25.213,
  "peNormalizedAnnual": 24.8766,
  "peTTM": 25.213,
  "pegTTM": 16.855250853942383,
  "pfcfShareAnnual": 31.7739,
  "pfcfShareTTM": 30.9852,
  "pretaxMargin5Y": 9.72,
  "pretaxMarginAnnual": 13.05,
  "pretaxMarginTTM": 12.69,
  "priceRelativeToS&P50013Week": 6.8883,
  "priceRelativeToS&P50026Week": -4.1379,
  "priceRelativeToS&P5004Week": 6.3998,
  "priceRelativeToS&P50052Week": -2.4185,
  "priceRelativeToS&P500Ytd": -7.9676,
  "psAnnual": 2.4615,
  "psTTM": 2.4193,
  "ptbvAnnual": 10.35104,
  "ptbvQuarterly": 9.68617,
  "quickRatioAnnual": 1.0494,
  "quickRatioQuarterly": 0.9278,
  "receivablesTurnoverAnnual": 153.5286,
  "receivablesTurnoverTTM": 109.56,
  "revenueEmployeeAnnual": 0.1975,
  "revenueEmployeeTTM": 0.2009,
  "revenueGrowth3Y": 3.76,
  "revenueGrowth5Y": 5.67,
  "revenueGrowthQuarterlyYoy": 4.57,
  "revenueGrowthTTMYoy": 1.92,
  "revenuePerShareAnnual": 63.8376,
  "revenuePerShareTTM": 66.1885,
  "revenueShareGrowth5Y": 7.52,
  "roa5Y": 10.34,
  "roaRfy": 14.030000000000001,
  "roaTTM": 14.08,
  "roe5Y": 31.34,
  "roeRfy": 37.95,
  "roeTTM": 37.37,
  "roi5Y": 20.59,
  "roiAnnual": 27.07,
  "roiTTM": 27.93,
  "tangibleBookValuePerShareAnnual": 12.51217,
  "tangibleBookValuePerShareQuarterly": 13.53373,
  "tbvCagr5Y": 7.05883,
  "totalDebt/totalEquityAnnual": 0.402,
  "totalDebt/totalEquityQuarterly": 0.2645,
  "yearToDatePriceReturnDaily": 7.2453
}